{"cameraMode":{"drawMode":0,"name":"Shaded","section":"Shading Mode"},"sceneLighting":true,"audioPlay":false,"sceneViewState":{"m_AlwaysRefresh":false,"showFog":true,"showSkybox":true,"showFlares":true,"showImageEffects":true,"showParticleSystems":true,"showVisualEffectGraphs":true,"m_FxEnabled":true},"in2DMode":false,"pivot":{"x":-11.796554565429688,"y":18.92645835876465,"z":-40.242408752441409},"rotation":{"x":0.05067010223865509,"y":-0.9427402019500732,"z":0.16862976551055909,"w":0.2832748293876648},"size":43.49704360961914,"orthographic":false}